iteratoraccelerator/__init__.py
iteratoraccelerator/iteratoraccelerator.py
iteratoraccelerator-0.0.9.dist-info/LICENSE
iteratoraccelerator-0.0.9.dist-info/METADATA
iteratoraccelerator-0.0.9.dist-info/WHEEL
iteratoraccelerator-0.0.9.dist-info/top_level.txt
iteratoraccelerator-0.0.9.dist-info/RECORD
