Metadata-Version: 2.1
Name: iteratoraccelerator
Version: 0.0.9
Summary: Binary iterator batcher
Home-page: https://github.com/SolvencyAnalytics/iteratoraccelerator
Author: Andras Kohlmann
Author-email: akohlmann@solvencyanalytics.com
License: UNKNOWN
Platform: UNKNOWN
Classifier: Programming Language :: Python :: 3
Classifier: Operating System :: OS Independent
Requires-Python: >=3.6
License-File: LICENSE
